esbonio/__main__.py
esbonio/cli/__init__.py
esbonio/cli/py.typed
esbonio/lsp/__init__.py
esbonio/lsp/log.py
esbonio/lsp/py.typed
esbonio/lsp/spelling.py
esbonio/lsp/symbols.py
esbonio/lsp/testing.py
esbonio/lsp/directives/__init__.py
esbonio/lsp/directives/completions.py
esbonio/lsp/roles/__init__.py
esbonio/lsp/roles/completions.py
esbonio/lsp/rst/__init__.py
esbonio/lsp/rst/__main__.py
esbonio/lsp/rst/config.py
esbonio/lsp/rst/directives.json
esbonio/lsp/rst/directives.py
esbonio/lsp/rst/io.py
esbonio/lsp/rst/roles.json
esbonio/lsp/rst/roles.py
esbonio/lsp/sphinx/__init__.py
esbonio/lsp/sphinx/__main__.py
esbonio/lsp/sphinx/autodoc.py
esbonio/lsp/sphinx/cli.py
esbonio/lsp/sphinx/codeblocks.py
esbonio/lsp/sphinx/config.py
esbonio/lsp/sphinx/directives.json
esbonio/lsp/sphinx/directives.py
esbonio/lsp/sphinx/domains.py
esbonio/lsp/sphinx/images.py
esbonio/lsp/sphinx/includes.py
esbonio/lsp/sphinx/line_number_transform.py
esbonio/lsp/sphinx/preview.py
esbonio/lsp/sphinx/roles.json
esbonio/lsp/sphinx/roles.py
esbonio/lsp/util/__init__.py
esbonio/lsp/util/filepaths.py
esbonio/lsp/util/inspect.py
esbonio/lsp/util/patterns.py
esbonio/lsp/util/resources.py
esbonio/server/__init__.py
esbonio/server/__main__.py
esbonio/server/_patterns.py
esbonio/server/_uri.py
esbonio/server/cli.py
esbonio/server/feature.py
esbonio/server/log.py
esbonio/server/server.py
esbonio/server/setup.py
esbonio/server/testing.py
esbonio/server/features/preview_manager/__init__.py
esbonio/server/features/preview_manager/webview.py
esbonio/server/features/sphinx_manager/__init__.py
esbonio/server/features/sphinx_manager/client.py
esbonio/server/features/sphinx_manager/client_subprocess.py
esbonio/server/features/sphinx_manager/config.py
esbonio/server/features/sphinx_manager/manager.py
esbonio/server/features/symbols/__init__.py
esbonio/server/features/symbols/io.py
esbonio/server/features/symbols/visitor.py
esbonio/sphinx_agent/__init__.py
esbonio/sphinx_agent/__main__.py
esbonio-0.16.5.dist-info/LICENSE
esbonio-0.16.5.dist-info/METADATA
esbonio-0.16.5.dist-info/WHEEL
esbonio-0.16.5.dist-info/entry_points.txt
esbonio-0.16.5.dist-info/top_level.txt
esbonio-0.16.5.dist-info/RECORD
