Metadata-Version: 2.1
Name: esbonio
Version: 0.16.5
Summary: A Language Server for Sphinx projects.
Home-page: https://docs.esbon.io/en/esbonio-language-server-v0.16.5/
Author: Alex Carney
Author-email: alcarneyme@gmail.com
License: MIT
Project-URL: Bug Tracker, https://github.com/swyddfa/esbonio/issues
Project-URL: Documentation, https://docs.esbon.io/en/esbonio-language-server-v0.16.5/
Project-URL: Source Code, https://github.com/swyddfa/esbonio
Platform: any
Classifier: Development Status :: 3 - Alpha
Classifier: License :: OSI Approved :: MIT License
Classifier: Programming Language :: Python
Classifier: Programming Language :: Python :: 3
Classifier: Programming Language :: Python :: 3 :: Only
Classifier: Programming Language :: Python :: 3.7
Classifier: Programming Language :: Python :: 3.8
Classifier: Programming Language :: Python :: 3.9
Classifier: Programming Language :: Python :: 3.10
Classifier: Programming Language :: Python :: 3.11
Classifier: Topic :: Documentation
Classifier: Topic :: Documentation :: Sphinx
Requires-Python: >=3.7
License-File: LICENSE
Requires-Dist: sphinx
Requires-Dist: platformdirs
Requires-Dist: pygls<2,>=1.1.0
Requires-Dist: pyspellchecker
Requires-Dist: typing-extensions; python_version < "3.8"
Provides-Extra: test
Requires-Dist: mock; python_version < "3.8" and extra == "test"
Requires-Dist: pytest; extra == "test"
Requires-Dist: pytest-lsp>=0.3.1; extra == "test"
Requires-Dist: pytest-asyncio<0.23; extra == "test"
Requires-Dist: pytest-cov; extra == "test"
Requires-Dist: pytest-timeout; extra == "test"
Provides-Extra: typecheck
Requires-Dist: mypy; extra == "typecheck"
Requires-Dist: pytest-lsp>=0.3.1; extra == "typecheck"
Requires-Dist: types-appdirs; extra == "typecheck"
Requires-Dist: types-docutils; extra == "typecheck"
Requires-Dist: types-pygments; extra == "typecheck"
Provides-Extra: dev
Requires-Dist: black; extra == "dev"
Requires-Dist: flake8; extra == "dev"
Requires-Dist: pre-commit; extra == "dev"
Requires-Dist: tox; extra == "dev"
